Workbook

Sheet Free Cash Flow
B2: Unlevered Free Cash Flow (mm)
B3: Fiscal Year | C3: 2022 | D3: 2023 | E3: 2024 | F3: 2025 | G3: 2026 | H3: 2027 | I3: 2028 | J3: 2029
B4: Revenue | C4: ='Income Statement'!C3 -> 1339464 | D4: ='Income Statement'!D3 -> 1367719 | E4: ='Income Statement'!E3 -> 1428716 | F4: =(1+F24)*E4 -> 1475643.5 | G4: =(1+G24)*F4 -> 1524112.4 | H4: =(1+H24)*G4 -> 1574173.3 | I4: =(1+I24)*H4 -> 1625878.5 | J4: =(1+J24)*I4 -> 1679282
B5: COGS | C5: ='Income Statement'!C4 -> -945966 | D5: ='Income Statement'!D4 -> -957187 | E5: ='Income Statement'!E4 -> -993243 | F5: =-(F25*F4) -> -1033574.6 | G5: =-(G25*G4) -> -1067523.3 | H5: =-(H25*H4) -> -1102587.1 | I5: =-(I25*I4) -> -1138802.6 | J5: =-(J25*J4) -> -1176207.7
B6: Gross Profit | C6: =C4+C5 -> 393498 | D6: =D4+D5 -> 410532 | E6: =E4+E5 -> 435473 | F6: =F4+F5 -> 442068.92 | G6: =G4+G5 -> 456589.09 | H6: =H4+H5 -> 471586.18 | I6: =I4+I5 -> 487075.87 | J6: =J4+J5 -> 503074.34
B7: Selling, General, Administrative | C7: ='Income Statement'!C7 -> -248619 | D7: ='Income Statement'!D7 -> -271035 | E7: ='Income Statement'!E7 -> -294995 | F7: =-(F26*F4) -> -290333.9 | G7: =-(G26*G4) -> -299870.19 | H7: =-(H26*H4) -> -309719.71 | I7: =-(I26*I4) -> -319892.74 | J7: =-(J26*J4) -> -330399.92
B8: Total Operating Expenses | C8: =-C7 -> 248619 | D8: =-D7 -> 271035 | E8: =-E7 -> 294995 | F8: =-F7 -> 290333.9 | G8: =-G7 -> 299870.19 | H8: =-H7 -> 309719.71 | I8: =-I7 -> 319892.74 | J8: =-J7 -> 330399.92
B9: EBITDA | C9: =C11+C10 -> 214738 | D9: =D11+D10 -> 208430 | E9: =E11+E10 -> 218137 | F9: =F11+F10 -> 228916.2 | G9: =G11+G10 -> 236435.16 | H9: =H11+H10 -> 244201.1 | I9: =I11+I10 -> 252222.11 | J9: =J11+J10 -> 260506.58
B10: Depreciation & Amortization | C10: ='Cash Flow Statement'!C4+'Cash Flow Statement'!C5 -> 52553 | D10: ='Cash Flow Statement'!D4+'Cash Flow Statement'!D5 -> 53016 | E10: ='Cash Flow Statement'!E4+'Cash Flow Statement'!E5 -> 58456 | F10: =F27*F4 -> 58490.455 | G10: =G27*G4 -> 60411.628 | H10: =H27*H4 -> 62395.905 | I10: =I27*I4 -> 64445.357 | J10: =J27*J4 -> 66562.125
B11: Operating Profit (EBIT) | C11: ='Income Statement'!C8 -> 162185 | D11: ='Income Statement'!D8 -> 155414 | E11: ='Income Statement'!E8 -> 159681 | F11: =F28*F4 -> 170425.74 | G11: =G28*G4 -> 176023.54 | H11: =H28*H4 -> 181805.19 | I11: =I28*I4 -> 187776.76 | J11: =J28*J4 -> 193944.46
B12: Operating Taxes | C12: =C29*C11 -> 29440 | D12: =D29*D11 -> 29124 | E12: =E29*E11 -> 30429 | F12: =F29*F11 -> 31783.181 | G12: =G29*G11 -> 32827.13 | H12: =H29*H11 -> 33905.368 | I12: =I29*I11 -> 35019.021 | J12: =J29*J11 -> 36169.253
B13: NOPAT (Net Operating Profit After Taxes) | C13: =C11-C12 -> 132745 | D13: =D11-D12 -> 126290 | E13: =E11-E12 -> 129252 | F13: =F11-F12 -> 138642.56 | G13: =G11-G12 -> 143196.41 | H13: =H11-H12 -> 147899.83 | I13: =I11-I12 -> 152757.73 | J13: =J11-J12 -> 157775.21
B14: (+) Depreciation & Amortization | C14: =C10 -> 52553 | D14: =D10 -> 53016 | E14: =E10 -> 58456 | F14: =F10 -> 58490.455 | G14: =G10 -> 60411.628 | H14: =H10 -> 62395.905 | I14: =I10 -> 64445.357 | J14: =J10 -> 66562.125
B15: (-) Capital Expenditures | C15: ='Fixed Assets'!C6 -> 8795 | D15: ='Fixed Assets'!D6 -> 10158 | E15: ='Fixed Assets'!E6 -> 18191 | F15: ='Fixed Assets'!F6 -> 12181.48 | G15: ='Fixed Assets'!G6 -> 11908.047 | H15: ='Fixed Assets'!H6 -> 11648.942 | I15: ='Fixed Assets'!I6 -> 11393.699 | J15: ='Fixed Assets'!J6 -> 11142.595
B16: (-) Change in NWC | C16: 0 | D16: =D17-C17 -> 50332 | E16: =E17-D17 -> -12714 | F16: =F17-E17 -> 4280.8843 | G16: =G17-F17 -> 3735.9709 | H16: =H17-G17 -> 7769.6857 | I16: =I17-H17 -> 3985.4244 | J16: =J17-I17 -> 8288.4732
B17: NWC | C17: =C18-C19 -> 130417 | D17: =D18-D19 -> 180749 | E17: =E18-E19 -> 168035 | F17: =F18-F19 -> 172315.88 | G17: =G18-G19 -> 176051.86 | H17: =H18-H19 -> 183821.54 | I17: =I18-I19 -> 187806.97 | J17: =J18-J19 -> 196095.44
B18: Current Assets | C18: ='Net Working Capital'!C7 -> 396221 | D18: ='Net Working Capital'!D7 -> 444738 | E18: ='Net Working Capital'!E7 -> 472290 | F18: ='Net Working Capital'!F7 -> 468046.01 | G18: ='Net Working Capital'!G7 -> 483419.42 | H18: ='Net Working Capital'!H7 -> 499297.78 | I18: ='Net Working Capital'!I7 -> 515697.69 | J18: ='Net Working Capital'!J7 -> 532636.26
B19: Current Liabilitites | C19: ='Net Working Capital'!C13 -> 265804 | D19: ='Net Working Capital'!D13 -> 263989 | E19: ='Net Working Capital'!E13 -> 304255 | F19: ='Net Working Capital'!F13 -> 295730.13 | G19: ='Net Working Capital'!G13 -> 307367.57 | H19: ='Net Working Capital'!H13 -> 315476.24 | I19: ='Net Working Capital'!I13 -> 327890.72 | J19: ='Net Working Capital'!J13 -> 336540.82
B20: Unlevered Free Cash Flow | C20: =C13+C14-C15-C16 -> 176503 | D20: =D13+D14-D15-D16 -> 118816 | E20: =E13+E14-E15-E16 -> 182231 | F20: =F13+F14-F15-F16 -> 180670.65 | G20: =G13+G14-G15-G16 -> 187964.02 | H20: =H13+H14-H15-H16 -> 190877.1 | I20: =I13+I14-I15-I16 -> 201823.97 | J20: =J13+J14-J15-J16 -> 204906.26
B22: Assumptions
B23: =B3 -> Fiscal Year | C23: {=C3:J3} -> 2022 | D23: 2023 | E23: 2024 | F23: 2025 | G23: 2026 | H23: 2027 | I23: 2028 | J23: 2029
B24: Revenue Growth | D24: =D4/C4-1 -> 0.021094259 | E24: =E4/D4-1 -> 0.044597611 | F24: =AVERAGE(D24:E24) -> 0.032845935 | G24: =F24 -> 0.032845935 | H24: =G24 -> 0.032845935 | I24: =H24 -> 0.032845935 | J24: =I24 -> 0.032845935
B25: COGS % of Revenue | C25: =-C5/C4 -> 0.70622727 | D25: =-D5/D4 -> 0.69984185 | E25: =-E5/E4 -> 0.69519975 | F25: =AVERAGE(C25:E25) -> 0.70042296 | G25: =F25 -> 0.70042296 | H25: =G25 -> 0.70042296 | I25: =H25 -> 0.70042296 | J25: =I25 -> 0.70042296
B26: SG&A % of Revenue | C26: =-C7/C4 -> 0.18561081 | D26: =-D7/D4 -> 0.19816571 | E26: =-E7/E4 -> 0.2064756 | F26: =AVERAGE(C26:E26) -> 0.19675071 | G26: =F26 -> 0.19675071 | H26: =G26 -> 0.19675071 | I26: =H26 -> 0.19675071 | J26: =I26 -> 0.19675071
B27: D&A % of Revenue | C27: =C10/C4 -> 0.03923435 | D27: =D10/D4 -> 0.038762348 | E27: =E10/E4 -> 0.040915059 | F27: =AVERAGE(C27:E27) -> 0.039637253 | G27: =F27 -> 0.039637253 | H27: =G27 -> 0.039637253 | I27: =H27 -> 0.039637253 | J27: =I27 -> 0.039637253
B28: EBIT Margin | C28: =C11/C4 -> 0.12108201 | D28: =D11/D4 -> 0.11363007 | E28: =E11/E4 -> 0.11176539 | F28: =AVERAGE(C28:E28) -> 0.11549249 | G28: =F28 -> 0.11549249 | H28: =G28 -> 0.11549249 | I28: =H28 -> 0.11549249 | J28: =I28 -> 0.11549249
B29: Tax % of EBIT | C29: =-'Income Statement'!C13/'Income Statement'!C8 -> 0.1815211 | D29: =-'Income Statement'!D13/'Income Statement'!D8 -> 0.18739624 | E29: =-'Income Statement'!E13/'Income Statement'!E8 -> 0.19056118 | F29: =AVERAGE(C29:E29) -> 0.18649284 | G29: =F29 -> 0.18649284 | H29: =G29 -> 0.18649284 | I29: =H29 -> 0.18649284 | J29: =I29 -> 0.18649284

Sheet Fixed Assets
B2: Fixed Assets Schedule
B3: Fiscal Year | C3: 2022 | D3: 2023 | E3: 2024 | F3: 2025 | G3: 2026 | H3: 2027 | I3: 2028 | J3: 2029
B4: Beginning PPE | C4: 302883 | D4: =C9 -> 291608 | E4: =D9 -> 283658 | F4: =E9 -> 304537 | G4: =F9 -> 297701.17 | H4: =G9 -> 291223.55 | I4: =H9 -> 284842.48 | J4: =I9 -> 278564.87
B5: Depreciation of PPE | C5: ='Cash Flow Statement'!C4 -> 19539 | D5: ='Cash Flow Statement'!D4 -> 17876 | E5: ='Cash Flow Statement'!E4 -> 17453 | F5: =F13*F4 -> 19017.305 | G5: =G13*G4 -> 18385.668 | H5: =H13*H4 -> 18030.013 | I5: =I13*I4 -> 17671.311 | J5: =J13*J4 -> 17243.995
B6: CapEx (Purchase of PPE) | C6: =-'Cash Flow Statement'!C20 -> 8795 | D6: =-'Cash Flow Statement'!D20 -> 10158 | E6: =-'Cash Flow Statement'!E20 -> 18191 | F6: =F14*F4 -> 12181.48 | G6: =G14*G4 -> 11908.047 | H6: =H14*H4 -> 11648.942 | I6: =I14*I4 -> 11393.699 | J6: =J14*J4 -> 11142.595
B7: Disposals | C7: ='Cash Flow Statement'!C19+'Cash Flow Statement'!C6 -> 129 | D7: ='Cash Flow Statement'!D19+'Cash Flow Statement'!D6 -> 94 | E7: ='Cash Flow Statement'!E19+'Cash Flow Statement'!E6 -> 108 | F7: 0 | G7: 0 | H7: 0 | I7: 0 | J7: 0
B8: Other Movements | C8: 402 | D8: 138 | E8: 20249 | F8: 0 | G8: 0 | H8: 0 | I8: 0 | J8: 0
B9: Ending PP&E | C9: =C4-C5+C6-C7-C8 -> 291608 | D9: =D4-D5+D6-D7-D8 -> 283658 | E9: =E4-E5+E6-E7+E8 -> 304537 | F9: =F4+F6-F5 -> 297701.17 | G9: =G4+G6-G5 -> 291223.55 | H9: =H4+H6-H5 -> 284842.48 | I9: =I4+I6-I5 -> 278564.87 | J9: =J4+J6-J5 -> 272463.47
B11: Assumptions
B12: Fiscal Year | C12: 2022 | D12: 2023 | E12: 2024 | F12: 2025 | G12: 2026 | H12: 2027 | I12: 2028 | J12: 2029
B13: D&A as a % of Beginning PPE | C13: =C5/C4 -> 0.064510058 | D13: =D5/D4 -> 0.061301473 | E13: =E5/E4 -> 0.061528319 | F13: =AVERAGE(C13:E13) -> 0.062446617 | G13: =AVERAGE(D13:F13) -> 0.061758803 | H13: =AVERAGE(E13:G13) -> 0.061911246 | I13: =AVERAGE(F13:H13) -> 0.062038889 | J13: =AVERAGE(G13:I13) -> 0.061902979
B14: CapEx as a % of Beginning PPE | C14: =C6/C4 -> 0.029037615 | D14: =D6/D4 -> 0.034834435 | E14: =E6/E4 -> 0.064130044 | F14: 0.04 | G14: 0.04 | H14: 0.04 | I14: 0.04 | J14: 0.04

Sheet Net Working Capital
B2: Net Working Capital
B3: Fiscal Year | C3: 2022 | D3: 2023 | E3: 2024 | F3: 2025 | G3: 2026 | H3: 2027 | I3: 2028 | J3: 2029
B4: Accounts Receivables | C4: ='Balance Sheet'!C8 -> 19540 | D4: ='Balance Sheet'!D8 -> 28535 | E4: ='Balance Sheet'!E8 -> 20501 | F4: =F20*F17/365 -> 24495.867 | G4: =G20*G17/365 -> 25300.457 | H4: =H20*H17/365 -> 26131.474 | I4: =I20*I17/365 -> 26989.787 | J4: =J20*J17/365 -> 27876.292
B5: Inventory | C5: ='Balance Sheet'!C7 -> 101182 | D5: ='Balance Sheet'!D7 -> 91802 | E5: ='Balance Sheet'!E7 -> 98426 | F5: =F21*F17/365 -> 104057.91 | G5: =G21*G17/365 -> 107475.79 | H5: =H21*H17/365 -> 111005.93 | I5: =I21*I17/365 -> 114652.03 | J5: =J21*J17/365 -> 118417.88
B6: Cash & Cash Equivalents | C6: ='Balance Sheet'!C9 -> 275499 | D6: ='Balance Sheet'!D9 -> 324401 | E6: ='Balance Sheet'!E9 -> 353363 | F6: =F24*F17 -> 339492.23 | G6: =G24*G17 -> 350643.17 | H6: =H24*H17 -> 362160.38 | I6: =I24*I17 -> 374055.87 | J6: =J24*J17 -> 386342.09
B7: Current Assets | C7: =SUM(C4:C6) -> 396221 | D7: =SUM(D4:D6) -> 444738 | E7: =SUM(E4:E6) -> 472290 | F7: =SUM(F4:F6) -> 468046.01 | G7: =SUM(G4:G6) -> 483419.42 | H7: =SUM(H4:H6) -> 499297.78 | I7: =SUM(I4:I6) -> 515697.69 | J7: =SUM(J4:J6) -> 532636.26
B9: Accounts Payable | C9: ='Balance Sheet'!C17 -> 197455 | D9: ='Balance Sheet'!D17 -> 199943 | E9: ='Balance Sheet'!E17 -> 230241 | F9: =F22*F18/365 -> 223743.78 | G9: =G22*G18/365 -> 231092.85 | H9: =H22*H18/365 -> 238683.31 | I9: =I22*I18/365 -> 246523.09 | J9: =J22*J18/365 -> 254620.37
B10: Tax Payable | C10: ='Balance Sheet'!C18 -> 35297 | D10: ='Balance Sheet'!D18 -> 29638 | E10: ='Balance Sheet'!E18 -> 32655 | F10: =F25*F17 -> 34863.272 | G10: =G25*G17 -> 36008.389 | H10: =H25*H17 -> 37191.118 | I10: =I25*I17 -> 38412.695 | J10: =J25*J17 -> 39674.396
B11: Provision for reinstatement costs | C11: ='Balance Sheet'!C19 -> - | D11: ='Balance Sheet'!D19 -> - | E11: ='Balance Sheet'!E19 -> 3613 | F11: ='Balance Sheet'!F19 -> 0 | G11: ='Balance Sheet'!G19 -> 0 | H11: ='Balance Sheet'!H19 -> 0 | I11: ='Balance Sheet'!I19 -> 0 | J11: ='Balance Sheet'!J19 -> 0
B12: Lease Liabilities | C12: ='Balance Sheet'!C20 -> 33052 | D12: ='Balance Sheet'!D20 -> 34408 | E12: ='Balance Sheet'!E20 -> 37746 | F12: =F27*F17 -> 37123.08 | G12: =G27*G17 -> 40266.328 | H12: =H27*H17 -> 39601.815 | I12: =I27*I17 -> 42954.94 | J12: =J27*J17 -> 42246.057
B13: Current Liabilities | C13: =SUM(C9:C12) -> 265804 | D13: =SUM(D9:D12) -> 263989 | E13: =SUM(E9:E12) -> 304255 | F13: =SUM(F9:F12) -> 295730.13 | G13: =SUM(G9:G12) -> 307367.57 | H13: =SUM(H9:H12) -> 315476.24 | I13: =SUM(I9:I12) -> 327890.72 | J13: =SUM(J9:J12) -> 336540.82
B15: Assumptions
B16: Fiscal Year | C16: 2022 | D16: 2023 | E16: 2024 | F16: 2025 | G16: 2026 | H16: 2027 | I16: 2028 | J16: 2029
B17: Revenue | C17: ='Free Cash Flow'!C4 -> 1339464 | D17: ='Free Cash Flow'!D4 -> 1367719 | E17: ='Free Cash Flow'!E4 -> 1428716 | F17: ='Free Cash Flow'!F4 -> 1475643.5 | G17: ='Free Cash Flow'!G4 -> 1524112.4 | H17: ='Free Cash Flow'!H4 -> 1574173.3 | I17: ='Free Cash Flow'!I4 -> 1625878.5 | J17: ='Free Cash Flow'!J4 -> 1679282
B18: COGS | C18: =-'Free Cash Flow'!C5 -> 945966 | D18: =-'Free Cash Flow'!D5 -> 957187 | E18: =-'Free Cash Flow'!E5 -> 993243 | F18: =-'Free Cash Flow'!F5 -> 1033574.6 | G18: =-'Free Cash Flow'!G5 -> 1067523.3 | H18: =-'Free Cash Flow'!H5 -> 1102587.1 | I18: =-'Free Cash Flow'!I5 -> 1138802.6 | J18: =-'Free Cash Flow'!J5 -> 1176207.7
B20: Days Sales Outstanding (DSO) | C20: =C4/C17*365 -> 5.3245925 | D20: =D4/D17*365 -> 7.6150693 | E20: =E4/E17*365 -> 5.2374755 | F20: =AVERAGE(C20:E20) -> 6.0590458 | G20: =F20 -> 6.0590458 | H20: =G20 -> 6.0590458 | I20: =H20 -> 6.0590458 | J20: =I20 -> 6.0590458
B21: Days Inventory Outstanding (DIO) | C21: =C5/C17*365 -> 27.571797 | D21: =D5/D17*365 -> 24.498987 | E21: =E5/E17*365 -> 25.145298 | F21: =AVERAGE(C21:E21) -> 25.738694 | G21: =F21 -> 25.738694 | H21: =G21 -> 25.738694 | I21: =H21 -> 25.738694 | J21: =I21 -> 25.738694
B22: Days Payable Outstanding (DPO) | C22: =C9/C18*365 -> 76.187807 | D22: =D9/D18*365 -> 76.243404 | E22: =E9/E18*365 -> 84.609673 | F22: =AVERAGE(C22:E22) -> 79.013628 | G22: =F22 -> 79.013628 | H22: =G22 -> 79.013628 | I22: =H22 -> 79.013628 | J22: =I22 -> 79.013628
B24: Cash as a % of Revenue | C24: ='Net Working Capital'!C6/'Net Working Capital'!C17 -> 0.20567854 | D24: ='Net Working Capital'!D6/'Net Working Capital'!D17 -> 0.23718395 | E24: ='Net Working Capital'!E6/'Net Working Capital'!E17 -> 0.24732907 | F24: =AVERAGE(C24:E24) -> 0.23006385 | G24: =F24 -> 0.23006385 | H24: =G24 -> 0.23006385 | I24: =H24 -> 0.23006385 | J24: =I24 -> 0.23006385
B25: Tax Payable as a % of Revenue | C25: =C10/C17 -> 0.026351585 | D25: =D10/D17 -> 0.021669656 | E25: =E10/E17 -> 0.022856187 | F25: =AVERAGE(C25:E25) -> 0.023625809 | G25: =F25 -> 0.023625809 | H25: =G25 -> 0.023625809 | I25: =H25 -> 0.023625809 | J25: =I25 -> 0.023625809
B26: Provision for reinstatement costs as a % of Revenue | C26: =0/C17 -> 0 | D26: =0/D17 -> 0 | E26: =E11/E17 -> 0.0025288441 | F26: 0 | G26: 0 | H26: 0 | I26: 0 | J26: 0
B27: Lease Liabilities as a % of Revenue | C27: =C12/C17 -> 0.024675542 | D27: =D12/D17 -> 0.025157214 | E27: =E12/E17 -> 0.026419526 | F27: =D27 -> 0.025157214 | G27: =E27 -> 0.026419526 | H27: =F27 -> 0.025157214 | I27: =G27 -> 0.026419526 | J27: =H27 -> 0.025157214

Sheet DCF
B2: Unlevered Free Cash Flow (mm)
B3: Fiscal Year | D3: 2022 | E3: 2023 | F3: 2024 | G3: 2025 | H3: 2026 | I3: 2027 | J3: 2028 | K3: 2029
B4: Unlevered Free Cash Flow | D4: ='Free Cash Flow'!C20 -> 176503 | E4: ='Free Cash Flow'!D20 -> 118816 | F4: ='Free Cash Flow'!E20 -> 182231 | G4: ='Free Cash Flow'!F20 -> 180670.65 | H4: ='Free Cash Flow'!G20 -> 187964.02 | I4: ='Free Cash Flow'!H20 -> 190877.1 | J4: ='Free Cash Flow'!I20 -> 201823.97 | K4: ='Free Cash Flow'!J20 -> 204906.26
B6: Projection Year | G6: 1 | H6: 2 | I6: 3 | J6: 4 | K6: 5
B7: Present Value of Free Cash Flow | G7: =G4/(1+$C$12)^G6 -> 169535.06 | H7: =H4/(1+$C$12)^H6 -> 165507.83 | I7: =I4/(1+$C$12)^I6 -> 157713.76 | J7: =J4/(1+$C$12)^J6 -> 156480.57 | K7: =K4/(1+$C$12)^K6 -> 149078.43
B9: Implied Share Price Calculation | E9: Sensitivity Table
B10: Sum of PV of FCF | C10: =SUM(G7:K7) -> 798315.65
B11: Growth Rate | C11: 0.02 | G11: Growth Rate
B12: WACC | C12: =WACC!C18 -> 0.065683111 | F12: =C21 -> 2.8931051 | G12: =H12-0.5% -> 0.01 | H12: =I12-0.5% -> 0.015 | I12: 0.02 | J12: =I12+0.5% -> 0.025 | K12: =J12+0.5% -> 0.03
B13: Terminal Value | C13: =K4*(1+C11)/(C12-C11) -> 4575091 | E13: WACC | F13: =F14-0.5% -> 0.055683111 | G13: 2.9921396 | H13: 3.2872424 | I13: 3.6650461 | J13: 4.1659807 | K13: 4.8619596
B14: PV of Terminal Value | C14: =C13/(1+C12)^K6 -> 3328582.5 | F14: =F15-0.5% -> 0.060683111 | G14: 2.7096084 | H14: 2.9420511 | I14: 3.2316287 | J14: 3.6023589 | K14: 4.0939145
B15: Enterprise Value | C15: =C14+C10 -> 4126898.1 | F15: 0.065683111 | G15: 2.4778491 | H15: 2.6649942 | I15: 2.8931051 | J15: 3.1772863 | K15: 3.5411076
B16: (+) Cash | C16: ='Balance Sheet'!E9 -> 353363 | F16: =F15+0.5% -> 0.070683111 | G16: 2.284311 | H16: 2.4377169 | I16: 2.6213906 | J16: 2.8452703 | K16: 3.1241801
B17: (-) Debt | C17: =WACC!C4 -> 125617 | F17: =F16+0.5% -> 0.075683111 | G17: 2.1202648 | H17: 2.2479141 | I17: 2.3984876 | J17: 2.57877 | K17: 2.798516
B18: (-) Minority Interest | C18: ='Balance Sheet'!E28 -> 3414
B19: Equity Value | C19: =C15+C16-C17-C18 -> 4351230.1
B20: Diluted Shares Outstanding (mm) | C20: 1504000
B21: Implied Share Price | C21: =C19/C20 -> 2.8931051

Sheet WACC
B2: Weighted Average Cost of Capital (WACC)
B3: Equity (mm) | C3: ='Balance Sheet'!E29 -> 538337
B4: Debt (mm) | C4: ='Balance Sheet'!E13+'Balance Sheet'!E20 -> 125617
B6: Cost of Debt | C6: =-'Income Statement'!E11/WACC!F9 -> 0.039304677 | E6: Cost of Debt | F6: 2023 | G6: 2024
B7: Tax Rate | C7: =-'Income Statement'!E13/'Income Statement'!E12 -> 0.18117892 | E7: Total Lease Debt | F7: ='Balance Sheet'!D13+'Balance Sheet'!D20 -> 101328 | G7: ='Balance Sheet'!E13+'Balance Sheet'!E20 -> 125617
B8: D/(D+E) | C8: =C4/(C4+C3) -> 0.18919534
B9: After Tax Cost of Debt | C9: =C6*(1-C7) -> 0.032183498 | E9: Average Debt | F9: =(F7+G7)/2 -> 113472.5
B11: Risk Free Rate | C11: 0.035
B12: Expected Market Return | C12: =C11+C13 -> 0.09
B13: Market Risk Premium | C13: 0.055
B14: Levered Beta | C14: 0.7
B15: E/(D+E) | C15: =C3/(C3+C4) -> 0.81080466
B16: Cost of Equity | C16: =C11+C14*(C13) -> 0.0735
B18: WACC | C18: =C9*C8+C16*C15 -> 0.065683111

Sheet Income Statement
B2: Income Statement | C2: 2022 | D2: 2023 | E2: 2024
B3: Revenue | C3: 1339464 | D3: 1367719 | E3: 1428716
B4: Cost of Sales (COGS) | C4: -945966 | D4: -957187 | E4: -993243
B5: Gross Profit | C5: =SUM(C3:C4) -> 393498 | D5: =D3+D4 -> 410532 | E5: =E3+E4 -> 435473
B6: Other Income | C6: 17306 | D6: 15917 | E6: 19203
B7: SG&A | C7: =-7855-236217-4547 -> -248619 | D7: =-221425-49610 -> -271035 | E7: =-236484-58511 -> -294995
B8: Operating Profit (EBIT) | C8: =C5+C6+C7 -> 162185 | D8: =D5+D6+D7 -> 155414 | E8: =E5+E6+E7 -> 159681
B10: Finance Income | C10: 3674 | D10: 11224 | E10: 12729
B11: Finance Expenses | C11: -2777 | D11: -3518 | E11: -4460
B12: Profit Before Tax (PBT) | C12: =C8+C10+C11 -> 163082 | D12: =D8+D10+D11 -> 163120 | E12: =E8+E10+E11 -> 167950
B13: Tax Expense | C13: -29440 | D13: -29124 | E13: -30429
B14: Net Income | C14: =C12+C13 -> 133642 | D14: =D12+D13 -> 133996 | E14: =E12+E13 -> 137521

Sheet Balance Sheet
B2: Balance Sheet | C2: 2022 | D2: 2023 | E2: 2024
B3: Property, Plant & Equipment (PP&E) | C3: 291608 | D3: 283658 | E3: 304537
B4: Right-of-use Assets (ROU) | C4: 97286 | D4: 101797 | E4: 128314
B5: Investment Property | C5: - | D5: - | E5: 30000
B6: Total Non-Current Assets | C6: =SUM(C3:C5) -> 388894 | D6: =SUM(D3:D5) -> 385455 | E6: =SUM(E3:E5) -> 462851
B7: Inventories | C7: 101182 | D7: 91802 | E7: 98426
B8: Accounts Receivable | C8: 19540 | D8: 28535 | E8: 20501
B9: Cash & Cash Equivalents | C9: 275499 | D9: 324401 | E9: 353363
B10: Total Current Assets | C10: =SUM(C7:C9) -> 396221 | D10: =SUM(D7:D9) -> 444738 | E10: =SUM(E7:E9) -> 472290
B11: Total Assets | C11: =C6+C10 -> 785115 | D11: =D6+D10 -> 830193 | E11: =E6+E10 -> 935141
B13: Lease Liabilities | C13: 62598 | D13: 66920 | E13: 87871
B14: Provision for reinstatement costs | C14: - | D14: - | E14: 3417
B15: Deferred Tax Liabilities | C15: 1540 | D15: 2306 | E15: 1261
B16: Total Non-Current Liabilities | C16: =SUM(C13:C15) -> 64138 | D16: =SUM(D13:D15) -> 69226 | E16: =SUM(E13:E15) -> 92549
B17: Accounts Payable | C17: 197455 | D17: 199943 | E17: 230241
B18: Tax Payable | C18: 35297 | D18: 29638 | E18: 32655
B19: Provision for reinstatement costs | C19: - | D19: - | E19: 3613
B20: Lease Liabilities | C20: 33052 | D20: 34408 | E20: 37746
B21: Total Current Liabilities | C21: =SUM(C17:C20) -> 265804 | D21: =SUM(D17:D20) -> 263989 | E21: =SUM(E17:E20) -> 304255
B22: Total Liabilities | C22: =C21+C16 -> 329942 | D22: =D21+D16 -> 333215 | E22: =E21+E16 -> 396804
B24: Share Capital | C24: 235373 | D24: 235373 | E24: 235373
B25: Reserves | C25: =-68234-590+156 -> -68668 | D25: =-68234-695+218 -> -68711 | E25: =-68234-378+195 -> -68417
B26: Accumulated Profits | C26: 285541 | D26: 327113 | E26: 367967
B27: Shareholders' Equity | C27: =SUM(C24:C26) -> 452246 | D27: =SUM(D24:D26) -> 493775 | E27: =SUM(E24:E26) -> 534923
B28: Non-Controlling Interest (NCI) | C28: 2927 | D28: 3203 | E28: 3414
B29: Total Equity | C29: =SUM(C27:C28) -> 455173 | D29: =SUM(D27:D28) -> 496978 | E29: =SUM(E27:E28) -> 538337
B30: Balance Check: | C30: =C11-C29-C22 -> 0 | D30: =D11-D29-D22 -> 0 | E30: =E11-E29-E22 -> 0

Sheet Cash Flow Statement
B2: Cash Flow Statement | C2: 2022 | D2: 2023 | E2: 2024
B3: Net Income | C3: ='Income Statement'!C14 -> 133642 | D3: ='Income Statement'!D14 -> 133996 | E3: ='Income Statement'!E14 -> 137521
B4: Depreciation of PPE | C4: =19539 -> 19539 | D4: =17876 -> 17876 | E4: =17453 -> 17453
B5: Depreciation of ROU | C5: 33014 | D5: 35140 | E5: 41003
B6: Gain on disposal of PPE | C6: -20 | D6: -11 | E6: -49
B7: Gain on derecognition of ROU | C7: -12 | D7: - | E7: -
B8: Unrealised Exchange Gain | C8: -1017 | D8: -205 | E8: -1188
B9: Interest Income | C9: -3674 | D9: -11224 | E9: -12729
B10: Interest Expense | C10: 2777 | D10: 3518 | E10: 4460
B11: Tax Expense | C11: 29440 | D11: 29124 | E11: 30429
B12: Operating Profit before WC Changes | C12: =C3+SUM(C4:C11) -> 213689 | D12: =D3+SUM(D4:D11) -> 208214 | E12: =E3+SUM(E4:E11) -> 216900
B13: Change in Inventories | C13: -2799 | D13: 9380 | E13: -6624
B14: Change in Accounts Receivable | C14: -7936 | D14: -8995 | E14: 8047
B15: Change in Accounts Payable | C15: -14936 | D15: 2488 | E15: 29822
B16: Taxes Paid | C16: -21213 | D16: -34017 | E16: -29153
B17: Cash Flow from Operations (CFO) | C17: =C12+SUM(C13:C16) -> 166805 | D17: =D12+SUM(D13:D16) -> 177070 | E17: =E12+SUM(E13:E16) -> 218992
B19: Proceeds from disposal of PPE | C19: 149 | D19: 105 | E19: 157
B20: Purchase of PPE | C20: -8795 | D20: -10158 | E20: -18191
B21: Acquisition of a Subsidiary | C21: - | D21: - | E21: -49041
B22: Interest Received | C22: 3674 | D22: 11224 | E22: 12729
B23: Cash Flow from Investing (CFI) | C23: =SUM(C19:C22) -> -4972 | D23: =SUM(D19:D22) -> 1171 | E23: =SUM(E19:E22) -> -54346
B25: Dividends Paid | C25: -93971 | D25: -92016 | E25: -96226
B26: Repayment of Borrowing | C26: -5000 | D26: - | E26: -
B27: Payment of Lease Liabilities | C27: -31938 | D27: -34171 | E27: -36469
B28: Interest Paid on Lease Liabilities | C28: -2569 | D28: -3276 | E28: -4208
B29: Cash Flow from Financing (CFF) | C29: =SUM(C25:C28) -> -133478 | D29: =SUM(D25:D28) -> -129463 | E29: =SUM(E25:E28) -> -136903
B31: Net Increase/(Decrease) in Cash | C31: 28355 | D31: 48778 | E31: 27743
B32: Opening Cash Balance | C32: 246642 | D32: 275499 | E32: 324401
B33: FX Changes | C33: 502 | D33: 124 | E33: 1219
B34: Closing Cash Balance | C34: =SUM(C31:C33) -> 275499 | D34: =SUM(D31:D33) -> 324401 | E34: =SUM(E31:E33) -> 353363
